crealand/__init__.py
crealand/_apis/__init__.py
crealand/_apis/_constants.py
crealand/_apis/_subscribe_event.py
crealand/_apis/ai.py
crealand/_apis/detect.py
crealand/_apis/event.py
crealand/_apis/interactive.py
crealand/_apis/media.py
crealand/_apis/object.py
crealand/_apis/sensor.py
crealand/_core/__init__.py
crealand/_core/bridge/__init__.py
crealand/_core/bridge/_interface.py
crealand/_core/websocket/__init__.py
crealand/_core/websocket/websocket_client.py
crealand/_utils/__init__.py
crealand/_utils/_logger_setup.py
crealand/_utils/_utils.py
crealand-1.0.62.dist-info/licenses/LICENSE
samples/_wsdump.py
samples/main.py
crealand-1.0.62.dist-info/METADATA
crealand-1.0.62.dist-info/WHEEL
crealand-1.0.62.dist-info/top_level.txt
crealand-1.0.62.dist-info/RECORD
