Metadata-Version: 2.4
Name: crealand
Version: 1.0.62
Summary: Python SDK for the Crealand
Author-email: UBTECH Robotics <swenggroup@ubtrobot.com>
License: MIT License
Keywords: Crealand,UBTECH Robotics Crealand
Platform: Linux
Platform: Windows
Requires-Python: >=3.8
License-File: LICENSE
Requires-Dist: websockets
Dynamic: license-file
